README.md
setup.py
TOPSIS_Vaibhav_101803499.egg-info/PKG-INFO
TOPSIS_Vaibhav_101803499.egg-info/SOURCES.txt
TOPSIS_Vaibhav_101803499.egg-info/dependency_links.txt
TOPSIS_Vaibhav_101803499.egg-info/entry_points.txt
TOPSIS_Vaibhav_101803499.egg-info/requires.txt
TOPSIS_Vaibhav_101803499.egg-info/top_level.txt
src/topsis.py